<?xml version="1.0" encoding="UTF-8"?>
<!DOCTYPE mapper PUBLIC "-//mybatis.org//DTD Mapper 3.0//EN" "http://mybatis.org/dtd/mybatis-3-mapper.dtd">
<mapper namespace="com.dwinovo.ling_cloud.mapper.FileOwnershipMapper">

    <!-- 结果映射 -->
    <resultMap id="FileOwnershipResultMap" type="com.dwinovo.ling_cloud.pojo.FileOwnership">
        <id column="id" property="id"/>
        <result column="file_id" property="fileId"/>
        <result column="files_hash" property="filesHash"/>
        <result column="user_id" property="userId"/>
        <result column="created_at" property="createdAt"/>
        <result column="updated_at" property="updatedAt"/>
    </resultMap>

    <!-- 检查用户是否拥有指定文件 -->
    <select id="findByUserAndFile" resultMap="FileOwnershipResultMap">
        SELECT id, file_id, files_hash, user_id, created_at, updated_at
        FROM files_owner
        WHERE user_id = #{userId} AND file_id = #{fileId}
        LIMIT 1
    </select>

    <!-- 添加文件拥有关系 -->
    <insert id="insert" parameterType="com.dwinovo.ling_cloud.pojo.FileOwnership">
        INSERT INTO files_owner (id, file_id, files_hash, user_id, created_at, updated_at)
        VALUES (#{id}, #{fileId}, #{filesHash}, #{userId}, #{createdAt}, #{updatedAt})
    </insert>

    <!-- 删除指定用户的文件拥有关系 -->
    <delete id="deleteByUserAndFile">
        DELETE FROM files_owner
        WHERE user_id = #{userId} AND file_id = #{fileId}
    </delete>

    <!-- 统计文件拥有者数量 -->
    <select id="countByFileId" resultType="int">
        SELECT COUNT(1)
        FROM files_owner
        WHERE file_id = #{fileId}
    </select>

</mapper>
